wasapi/__init__.py
wasapi-0.1.0.dist-info/METADATA
wasapi-0.1.0.dist-info/WHEEL
wasapi-0.1.0.dist-info/entry_points.txt
wasapi-0.1.0.dist-info/top_level.txt
wasapi-0.1.0.dist-info/RECORD
