Metadata-Version: 2.4
Name: wasapi
Version: 0.1.0
Summary: A simple REST API using Flask
Home-page: https://github.com/yourusername/wasapi
Author: ucea-cse-2026
Author-email: newtonbaskar04@gmail.com
Classifier: Programming Language :: Python :: 3
Classifier: Framework :: Flask
Classifier: License :: OSI Approved :: MIT License
Classifier: Operating System :: OS Independent
Requires-Python: >=3.6
Requires-Dist: flask
Dynamic: author
Dynamic: author-email
Dynamic: classifier
Dynamic: description
Dynamic: description-content-type
Dynamic: home-page
Dynamic: requires-dist
Dynamic: requires-python
Dynamic: summary
